netbox_panorama_configpump_plugin/__init__.py
netbox_panorama_configpump_plugin/api/__init__.py
netbox_panorama_configpump_plugin/api/filtersets.py
netbox_panorama_configpump_plugin/api/serializers.py
netbox_panorama_configpump_plugin/api/urls.py
netbox_panorama_configpump_plugin/api/views.py
netbox_panorama_configpump_plugin/connection/__init__.py
netbox_panorama_configpump_plugin/connection/filtersets.py
netbox_panorama_configpump_plugin/connection/forms.py
netbox_panorama_configpump_plugin/connection/models.py
netbox_panorama_configpump_plugin/connection/tables.py
netbox_panorama_configpump_plugin/connection/template_code.py
netbox_panorama_configpump_plugin/connection/views.py
netbox_panorama_configpump_plugin/connection_template/__init__.py
netbox_panorama_configpump_plugin/connection_template/filtersets.py
netbox_panorama_configpump_plugin/connection_template/forms.py
netbox_panorama_configpump_plugin/connection_template/models.py
netbox_panorama_configpump_plugin/connection_template/tables.py
netbox_panorama_configpump_plugin/connection_template/views.py
netbox_panorama_configpump_plugin/device_config_sync_status/__init__.py
netbox_panorama_configpump_plugin/device_config_sync_status/filtersets.py
netbox_panorama_configpump_plugin/device_config_sync_status/forms.py
netbox_panorama_configpump_plugin/device_config_sync_status/jobs.py
netbox_panorama_configpump_plugin/device_config_sync_status/models.py
netbox_panorama_configpump_plugin/device_config_sync_status/panorama.py
netbox_panorama_configpump_plugin/device_config_sync_status/tables.py
netbox_panorama_configpump_plugin/device_config_sync_status/template_code.py
netbox_panorama_configpump_plugin/device_config_sync_status/views.py
netbox_panorama_configpump_plugin/migrations/0001_initial.py
netbox_panorama_configpump_plugin/migrations/0002_deviceconfigsyncstatus_deduce_xpaths_and_more.py
netbox_panorama_configpump_plugin/migrations/__init__.py
netbox_panorama_configpump_plugin/models.py
netbox_panorama_configpump_plugin-1.0.6.dist-info/METADATA
netbox_panorama_configpump_plugin-1.0.6.dist-info/WHEEL
netbox_panorama_configpump_plugin-1.0.6.dist-info/licenses/LICENSE
netbox_panorama_configpump_plugin-1.0.6.dist-info/RECORD
