Metadata-Version: 2.4
Name: netbox-panorama-configpump-plugin
Version: 1.0.6
Summary: A NetBox plugin that synchronizes Palo Alto Networks Panorama configuration from NetBox data using a pull, diff and push workflow.
License: Apache-2.0
License-File: LICENSE
Author: Veikko Pankakoski
Author-email: veikko@rautanen.io
Requires-Python: >=3.11,<4.0
Classifier: License :: OSI Approved :: Apache Software License
Classifier: Operating System :: OS Independent
Classifier: Programming Language :: Python :: 3
Classifier: Programming Language :: Python :: 3.11
Classifier: Programming Language :: Python :: 3.12
Classifier: Programming Language :: Python :: 3.13
Classifier: Programming Language :: Python :: 3.14
Requires-Dist: lxml (>=5.0,<7.0)
Requires-Dist: xmldiff (>=2.7.0,<3.0.0)
Requires-Dist: xmltodict (>=0.13,<0.14)
Project-URL: Documentation, https://github.com/rautanen-io/netbox-panorama-configpump-plugin
Project-URL: Homepage, https://rautanen.io
Project-URL: Repository, https://github.com/rautanen-io/netbox-panorama-configpump-plugin
